device_user_agent-0.1.2.dist-info/METADATA
device_user_agent-0.1.2.dist-info/WHEEL
device_user_agent-0.1.2.dist-info/licenses/LICENSE
device_user_agent/__init__.py
device_user_agent/device_user_agent.py
device_user_agent-0.1.2.dist-info/RECORD
