Metadata-Version: 2.1
Name: device-user-agent
Version: 0.1.2
Summary: Parses user agent string built with the device_user-agent flutter package.
Author-Email: Sarbagya Dhaubanjar <sarbagyastha@gmail.com>
License: MIT
Classifier: Programming Language :: Python :: 3.12
Classifier: License :: OSI Approved :: MIT License
Classifier: Operating System :: OS Independent
Classifier: Typing :: Typed
Project-URL: Homepage, https://acmesoftware.com
Project-URL: Repository, https://github.com/AcmeSoftwareLLC/device_user_agent/tree/main/parser/python
Requires-Python: >=3.12
Requires-Dist: pydantic>=2.7.1
